{
  "method_requested": "permutation",
  "importance_source": "permutation_importance",
  "input_feature_count": 30,
  "selected_feature_count": 5,
  "dropped_feature_count": 25,
  "top_k": 15,
  "cumulative_importance_target": 0.95,
  "min_importance": 0.0,
  "max_samples": 20000,
  "n_repeats": 2,
  "selected_features": [
    "gap_mean",
    "gap_ewma",
    "ewma_freq",
    "freq_density",
    "size"
  ],
  "dropped_features": [
    "log_size",
    "type_code",
    "op_code",
    "ttl",
    "log_ttl",
    "recency",
    "log_recency",
    "count_w",
    "count_short",
    "count_mid",
    "count_long",
    "log_freq_seen",
    "last_gap",
    "prev_gap",
    "gap_std",
    "gap_cv",
    "burst_ratio",
    "acceleration",
    "unique_since_last",
    "log_unique_since_last",
    "byte_freq",
    "byte_ewma",
    "byte_count_w",
    "age_seen",
    "log_age_seen"
  ],
  "ranked_importance": [
    {
      "feature": "gap_mean",
      "importance": 0.4755163083411799
    },
    {
      "feature": "gap_ewma",
      "importance": 0.1707626687889331
    },
    {
      "feature": "ewma_freq",
      "importance": 0.12852025466549458
    },
    {
      "feature": "freq_density",
      "importance": 0.12061527377398139
    },
    {
      "feature": "size",
      "importance": 0.07169444784968099
    },
    {
      "feature": "gap_cv",
      "importance": 0.016730751714605516
    },
    {
      "feature": "unique_since_last",
      "importance": 0.009383574780940672
    },
    {
      "feature": "prev_gap",
      "importance": 0.0038457573596892033
    },
    {
      "feature": "type_code",
      "importance": 0.001960782971467145
    },
    {
      "feature": "byte_freq",
      "importance": 0.0005225710695010516
    },
    {
      "feature": "byte_count_w",
      "importance": 0.00044760868452657887
    },
    {
      "feature": "log_recency",
      "importance": 0.0
    },
    {
      "feature": "ttl",
      "importance": 0.0
    },
    {
      "feature": "log_ttl",
      "importance": 0.0
    },
    {
      "feature": "log_size",
      "importance": 0.0
    },
    {
      "feature": "op_code",
      "importance": 0.0
    },
    {
      "feature": "last_gap",
      "importance": 0.0
    },
    {
      "feature": "log_freq_seen",
      "importance": 0.0
    },
    {
      "feature": "count_mid",
      "importance": 0.0
    },
    {
      "feature": "count_long",
      "importance": 0.0
    },
    {
      "feature": "count_short",
      "importance": 0.0
    },
    {
      "feature": "count_w",
      "importance": 0.0
    },
    {
      "feature": "recency",
      "importance": 0.0
    },
    {
      "feature": "gap_std",
      "importance": 0.0
    },
    {
      "feature": "acceleration",
      "importance": 0.0
    },
    {
      "feature": "burst_ratio",
      "importance": 0.0
    },
    {
      "feature": "log_unique_since_last",
      "importance": 0.0
    },
    {
      "feature": "byte_ewma",
      "importance": 0.0
    },
    {
      "feature": "age_seen",
      "importance": 0.0
    },
    {
      "feature": "log_age_seen",
      "importance": 0.0
    }
  ]
}